csdir/__init__.py
csdir/__init__.pyi
csfile/__init__.py
csfile/__init__.pyi
csharp_like_file-0.0.6.dist-info/METADATA
csharp_like_file-0.0.6.dist-info/WHEEL
csharp_like_file-0.0.6.dist-info/top_level.txt
csharp_like_file-0.0.6.dist-info/RECORD
